{
    "document": {
        "type": "APL",
        "version": "1.0",
        "theme": "dark",
        "import": [
            {
                "name": "alexa-viewport-profiles",
                "version": "1.0.0"
            },
            {
                "name": "alexa-layouts",
                "version": "1.0.0"
            },
            {
                "name": "alexa-styles",
                "version": "1.0.0"
            }
        ],
        "resources": [
            {
                "description": "Stock color for the light theme",
                "colors": {
                    "colorTextPrimary": "#151920"
                }
            },
            {
                "description": "Stock color for the dark theme",
                "when": "${viewport.theme == 'dark'}",
                "colors": {
                    "colorTextPrimary": "#f0f1ef"
                }
            },
            {
                "description": "Standard font sizes",
                "dimensions": {
                    "textSizeBody": 40,
                    "textSizePrimary": 24,
                    "textSizePrimarySmall": 22,
                    "textSizePrimary2": 30,
                    "textSizePrimary3": 36,
                    "textSizeSecondary": 40,
                    "textSizeSecondaryHint": 23,
                    "textSizeAttribution": 12
                }
            },
            {
                "description": "Common spacing values",
                "dimensions": {
                    "spacingThin": 6,
                    "spacingSmall": 12,
                    "spacingMedium": 24,
                    "spacingLarge": 48,
                    "spacingExtraLarge": 72
                }
            },
            {
                "description": "Common margins and padding",
                "dimensions": {
                    "marginTop": 40,
                    "marginLeft": 60,
                    "marginRight": 60,
                    "marginBottom": 40
                }
            }
        ],
        "styles": {
            "textStyleBase": {
                "description": "Base font description; set color and core font family",
                "values": [
                    {
                        "color": "@colorTextPrimary",
                        "fontFamily": "Amazon Ember"
                    }
                ]
            },
            "textStyleBase0": {
                "description": "Thin version of basic font",
                "extend": "textStyleBase",
                "values": {
                    "fontWeight": "100"
                }
            },
            "textStyleBase1": {
                "description": "Light version of basic font",
                "extend": "textStyleBase",
                "values": {
                    "fontWeight": "300"
                }
            },
            "mixinBody": {
                "values": {
                    "fontSize": "@textSizeBody"
                }
            },
            "mixinPrimary": {
                "values": {
                    "fontSize": "@textSizePrimary"
                }
            },
            "mixinPrimarySmall": {
                "values": {
                    "fontSize": "@textSizePrimarySmall"
                }
            },
            "mixinPrimary2": {
                "values": {
                    "fontSize": "@textSizePrimary2"
                }
            },
            "mixinPrimary3": {
                "values": {
                    "fontSize": "@textSizePrimary3"
                }
            },
            "mixinSecondary": {
                "values": {
                    "fontSize": "@textSizeSecondary"
                }
            },
            "textStylePrimarySmall": {
                "extend": [
                    "textStyleBase1",
                    "mixinPrimarySmall"
                ]
            },
            "textStylePrimary": {
                "extend": [
                    "textStyleBase1",
                    "mixinPrimary"
                ]
            },
            "textStylePrimary2": {
                "extend": [
                    "textStyleBase1",
                    "mixinPrimary2"
                ]
            },
            "textStyleSecondary": {
                "extend": [
                    "textStyleBase0",
                    "mixinSecondary"
                ]
            },
            "textStyleSecondary2": {
                "extend": [
                    "textStyleBase1",
                    "mixinSecondary"
                ]
            },
            "textStyleBody": {
                "extend": [
                    "textStyleBase1",
                    "mixinBody"
                ]
            },
            "textStyleSecondaryHint": {
                "values": {
                    "fontFamily": "Bookerly",
                    "fontStyle": "italic",
                    "fontSize": "@textSizeSecondaryHint",
                    "color": "@colorTextPrimary"
                }
            },
            "textStyleVerySmall": {
                "values": {
                    "fontFamily": "Bookerly",
                    "fontSize": "@textSizeAttribution",
                    "color": "@colorTextPrimary"
                }
            }
        },
        "layouts": {
            "Home": {
                "items": [
                    {
                        "when": "${@viewportProfile == @hubRoundSmall}",
                        "type": "Container",
                        "direction": "column",
                        "width": "100vw",
                        "height": "100vh",
                        "items": [
                            {
                                "type": "Image",
                                "source": "${payload.musicManTemplateData.properties.GeneralSquareImageUrl}",
                                "scale": "best-fill",
                                "width": "100vw",
                                "height": "100vh",
                                "position": "absolute",
                                "overlayColor": "rgba(0, 0, 0, 0.6)"
                            },
                            {
                                "type": "AlexaHeader",
                                "headerAttributionImage": "${payload.musicManTemplateData.properties.LogoUrl}",
                                "headerTitle": "${payload.musicManTemplateData.title}"
                            },
                            {
                                "type": "Text",
                                "text": "<b>The Music Man</b>",
                                "style": "textStyleBody",
                                "width": "90vw",
                                "paddingLeft": "10vw",
                                "textAlign": "center"
                            },
                            {
                                "type": "ScrollView",
                                "width": "100vw",
                                "height": "50vh",
                                "item": [
                                    {
                                        "type": "Container",
                                        "direction": "column",
                                        "alignItems": "center",
                                        "paddingLeft": 30,
                                        "paddingRight": 30,
                                        "paddingBottom": 200,
                                        "items": [
                                            {
                                                "type": "Text",
                                                "text": "${payload.musicManTemplateData.properties.EventText[0]}",
                                                "paddingTop": 30,
                                                "style": "textStylePrimary",
                                                "width": "90vw",
                                                "textAlign": "center"
                                            },
                                            {
                                                "type": "Text",
                                                "text": "${payload.musicManTemplateData.properties.EventText[1]}",
                                                "paddingTop": 20,
                                                "style": "textStylePrimary",
                                                "width": "90vw",
                                                "textAlign": "center"
                                            },
                                            {
                                                "type": "Text",
                                                "text": "${payload.musicManTemplateData.properties.EventText[2]}",
                                                "paddingTop": 20,
                                                "style": "textStylePrimary",
                                                "width": "90vw",
                                                "textAlign": "center"
                                            },
                                            {
                                                "type": "Image",
                                                "source": "${payload.musicManTemplateData.properties.SongkickLogoUrl}",
                                                "width": 120,
                                                "height": 100,
                                                "scale": "best-fit",
                                                "align": "center"
                                            }
                                        ]
                                    }
                                ]
                            }
                        ]
                    },
                    {
                        "when": "${@viewportProfile == @hubLandscapeSmall}",
                        "type": "Container",
                        "width": "100vw",
                        "height": "100vh",
                        "items": [
                            {
                                "type": "Image",
                                "source": "${payload.musicManTemplateData.properties.BackgroundImageUrl}",
                                "scale": "best-fill",
                                "width": "100vw",
                                "height": "100vh",
                                "position": "absolute"
                            },
                            {
                                "type": "AlexaHeader",
                                "headerTitle": "${payload.musicManTemplateData.properties.Title}",
                                "headerAttributionImage": "${payload.musicManTemplateData.properties.LogoUrl}"
                            },
                            {
                                "type": "Container",
                                "direction": "row",
                                "paddingLeft": 30,
                                "paddingRight": 72,
                                "grow": 1,
                                "items": [
                                    {
                                        "type": "Image",
                                        "source": "${payload.musicManTemplateData.properties.GeneralSquareImageUrl}",
                                        "width": 240,
                                        "height": 260,
                                        "scale": "best-fit",
                                        "align": "center"
                                    },
                                    {
                                        "type": "Container",
                                        "direction": "column",
                                        "paddingLeft": 10,
                                        "paddingRight": 10,
                                        "grow": 1,
                                        "items": [
                                            {
                                                "type": "Text",
                                                "text": "<b>Welcome to The Music Man</b>",
                                                "style": "textStyleBody"
                                            },
                                            {
                                                "type": "ScrollView",
                                                "height": "50vh",
                                                "width": "100vh",
                                                "shrink": 1,
                                                "item": [
                                                    {
                                                        "type": "Container",
                                                        "items": [
                                                            {
                                                                "type": "Text",
                                                                "text": "${payload.musicManTemplateData.properties.EventText[0]}",
                                                                "paddingTop": 40,
                                                                "style": "textStylePrimary"
                                                            },
                                                            {
                                                                "type": "Text",
                                                                "text": "${payload.musicManTemplateData.properties.EventText[1]}",
                                                                "paddingTop": 20,
                                                                "style": "textStylePrimary"
                                                            },
                                                            {
                                                                "type": "Text",
                                                                "text": "${payload.musicManTemplateData.properties.EventText[2]}",
                                                                "paddingTop": 20,
                                                                "style": "textStylePrimary"
                                                            }
                                                        ]
                                                    }
                                                ]
                                            }
                                        ]
                                    }
                                ]
                            },
                            {
                                "type": "Container",
                                "direction": "row",
                                "paddingRight": 150,
                                "grow": 1,
                                "items": [
                                    {
                                        "type": "AlexaFooter",
                                        "footerHint": "${payload.musicManTemplateData.properties.HintString}",
                                        "height": 40
                                    },
                                    {
                                        "type": "Image",
                                        "source": "${payload.musicManTemplateData.properties.SongkickLogoUrl}",
                                        "width": 120,
                                        "height": 70,
                                        "scale": "best-fit",
                                        "align": "center"
                                    }
                                ]
                            },
                            {
                                "type": "Container",
                                "direction": "row",
                                "grow": 0,
                                "items": [
                                    {
                                        "type": "Text",
                                        "text": "${payload.musicManTemplateData.properties.PhotoAttribution}",
                                        "style": "textStyleVerySmall",
                                        "height": "100vw",
                                        "width": "100vw",
                                        "textAlign": "right",
                                        "paddingRight": 30
                                    }
                                ]
                            }
                        ]
                    },
                    {
                        "type": "Container",
                        "width": "100vw",
                        "height": "100vh",
                        "items": [
                            {
                                "type": "Image",
                                "source": "${payload.musicManTemplateData.properties.BackgroundImageUrl}",
                                "scale": "best-fill",
                                "width": "100vw",
                                "height": "100vh",
                                "position": "absolute"
                            },
                            {
                                "type": "AlexaHeader",
                                "headerTitle": "${payload.musicManTemplateData.properties.Title}",
                                "headerAttributionImage": "${payload.musicManTemplateData.properties.LogoUrl}"
                            },
                            {
                                "type": "Container",
                                "direction": "row",
                                "paddingLeft": 30,
                                "paddingRight": 72,
                                "grow": 1,
                                "items": [
                                    {
                                        "type": "Image",
                                        "width": "300",
                                        "height": "300",
                                        "source": "${payload.musicManTemplateData.properties.GeneralSquareImageUrl}",
                                        "scale": "best-fit",
                                        "align": "center"
                                    },
                                    {
                                        "type": "Container",
                                        "direction": "column",
                                        "paddingLeft": 10,
                                        "paddingRight": 10,
                                        "grow": 1,
                                        "items": [
                                            {
                                                "type": "Text",
                                                "text": "<b>Welcome to the Music Man</b>",
                                                "style": "textStyleBody"
                                            },
                                            {
                                                "type": "ScrollView",
                                                "height": "50vh",
                                                "width": "100vh",
                                                "shrink": 1,
                                                "item": [
                                                    {
                                                        "type": "Container",
                                                        "items": [
                                                            {
                                                                "type": "Text",
                                                                "style": "textStylePrimary",
                                                                "paddingTop": 40,
                                                                "text": "${payload.musicManTemplateData.properties.EventText[0]}"
                                                            },
                                                            {
                                                                "type": "Text",
                                                                "style": "textStylePrimary",
                                                                "paddingTop": 20,
                                                                "text": "${payload.musicManTemplateData.properties.EventText[1]}"
                                                            },
                                                            {
                                                                "type": "Text",
                                                                "style": "textStylePrimary",
                                                                "paddingTop": 20,
                                                                "text": "${payload.musicManTemplateData.properties.EventText[2]}"
                                                            }
                                                        ]
                                                    }
                                                ]
                                            }
                                        ]
                                    }
                                ]
                            },
                            {
                                "type": "Container",
                                "paddingRight": "150",
                                "direction": "row",
                                "grow": 1,
                                "items": [
                                    {
                                        "type": "AlexaFooter",
                                        "footerHint": "${payload.musicManTemplateData.properties.HintString}",
                                        "height": 60
                                    },
                                    {
                                        "type": "Image",
                                        "source": "${payload.musicManTemplateData.properties.SongkickLogoUrl}",
                                        "width": 120,
                                        "height": 80,
                                        "scale": "best-fit",
                                        "align": "center"
                                    }
                                ]
                            },
                            {
                                "type": "Container",
                                "direction": "row",
                                "items": [
                                    {
                                        "type": "Text",
                                        "text": "${payload.musicManTemplateData.properties.PhotoAttribution}",
                                        "style": "textStyleVerySmall",
                                        "paddingTop": 10,
                                        "height": "100vw",
                                        "width": "100vw",
                                        "textAlign": "right",
                                        "paddingRight": 30
                                    }
                                ]
                            }
                        ]
                    }
                ]
            },
            "Main": {
                "items": [
                    {
                        "when": "${@viewportProfile == @hubRoundSmall}",
                        "type": "Container",
                        "direction": "column",
                        "width": "100vw",
                        "height": "100vh",
                        "items": [
                            {
                                "type": "Image",
                                "source": "${payload.musicManTemplateData.properties.GeneralSquareImageUrl}",
                                "scale": "best-fill",
                                "width": "100vw",
                                "height": "100vh",
                                "position": "absolute",
                                "overlayColor": "rgba(0, 0, 0, 0.6)"
                            },
                            {
                                "type": "ScrollView",
                                "width": "100vw",
                                "height": "100vh",
                                "item": [
                                    {
                                        "type": "Container",
                                        "direction": "column",
                                        "alignItems": "center",
                                        "paddingLeft": 30,
                                        "paddingRight": 30,
                                        "paddingBottom": 200,
                                        "items": [
                                            {
                                                "type": "AlexaHeader",
                                                "headerAttributionImage": "${payload.musicManTemplateData.properties.LogoUrl}",
                                                "headerTitle": "${payload.musicManTemplateData.properties.Title}"
                                            },
                                            {
                                                "type": "Text",
                                                "text": "<b>${payload.musicManTemplateData.properties.HeadingText}</b>",
                                                "style": "textStyleBody",
                                                "width": "80vw",
                                                "textAlign": "center"
                                            },
                                            {
                                                "type": "Text",
                                                "text": "${payload.musicManTemplateData.properties.EventText[0]}",
                                                "paddingTop": 40,
                                                "style": "textStylePrimary",
                                                "width": "80vw",
                                                "textAlign": "center"
                                            },
                                            {
                                                "type": "Text",
                                                "text": "${payload.musicManTemplateData.properties.EventText[1]}",
                                                "paddingTop": 40,
                                                "style": "textStylePrimary",
                                                "width": "80vw",
                                                "textAlign": "center"
                                            },
                                            {
                                                "type": "Text",
                                                "text": "${payload.musicManTemplateData.properties.EventText[2]}",
                                                "paddingTop": 40,
                                                "style": "textStylePrimary",
                                                "width": "80vw",
                                                "textAlign": "center"
                                            },
                                            {
                                                "type": "Image",
                                                "source": "${payload.musicManTemplateData.properties.SongkickLogoUrl}",
                                                "width": 120,
                                                "height": 100,
                                                "scale": "best-fit",
                                                "align": "center"
                                            }
                                        ]
                                    }
                                ]
                            }
                        ]
                    },
                    {
                        "when": "${@viewportProfile == @hubLandscapeSmall}",
                        "type": "Container",
                        "width": "100vw",
                        "height": "100vh",
                        "items": [
                            {
                                "type": "Image",
                                "source": "${payload.musicManTemplateData.properties.BackgroundImageUrl}",
                                "scale": "best-fill",
                                "width": "100vw",
                                "height": "100vh",
                                "position": "absolute"
                            },
                            {
                                "type": "AlexaHeader",
                                "headerTitle": "${payload.musicManTemplateData.properties.Title}",
                                "headerAttributionImage": "${payload.musicManTemplateData.properties.LogoUrl}"
                            },
                            {
                                "type": "Container",
                                "direction": "row",
                                "paddingLeft": 40,
                                "paddingRight": 60,
                                "grow": 1,
                                "items": [
                                    {
                                        "type": "Container",
                                        "items": [
                                            {
                                                "when": "${payload.musicManTemplateData.properties.EventImageUrl != 'NA'}",
                                                "type": "Image",
                                                "source": "${payload.musicManTemplateData.properties.EventImageUrl}",
                                                "width": 240,
                                                "height": 260,
                                                "scale": "best-fit",
                                                "align": "top"
                                            },
                                            {
                                                "when": "${payload.musicManTemplateData.properties.EventImageUrl == 'NA'}",
                                                "type": "Image",
                                                "source": "${payload.musicManTemplateData.properties.GeneralSquareImageUrl}",
                                                "width": 240,
                                                "height": 260,
                                                "scale": "best-fit",
                                                "align": "top"
                                            }
                                        ]
                                    },
                                    {
                                        "type": "Container",
                                        "direction": "column",
                                        "paddingLeft": 15,
                                        "width": "63vw",
                                        "items": [
                                            {
                                                "type": "Text",
                                                "style": "textStylePrimary",
                                                "text": "<b>${payload.musicManTemplateData.properties.HeadingText}</b>"
                                            },
                                            {
                                                "type": "Text",
                                                "style": "textStylePrimarySmall",
                                                "paddingTop": 20,
                                                "text": "${payload.musicManTemplateData.properties.EventText[0]}"
                                            },
                                            {
                                                "type": "Text",
                                                "text": "${payload.musicManTemplateData.properties.EventText[1]}",
                                                "paddingTop": 20,
                                                "style": "textStylePrimarySmall"
                                            },
                                            {
                                                "type": "Text",
                                                "text": "${payload.musicManTemplateData.properties.EventText[2]}",
                                                "paddingTop": 20,
                                                "style": "textStylePrimarySmall"
                                            }
                                        ]
                                    }
                                ]
                            },
                            {
                                "type": "Container",
                                "direction": "row",
                                "paddingRight": 150,
                                "paddingTop": 10,
                                "grow": 1,
                                "items": [
                                    {
                                        "type": "AlexaFooter",
                                        "footerHint": "${payload.musicManTemplateData.properties.HintString}",
                                        "height": 60
                                    },
                                    {
                                        "type": "Image",
                                        "source": "${payload.musicManTemplateData.properties.SongkickLogoUrl}",
                                        "width": 120,
                                        "height": 80,
                                        "scale": "best-fit",
                                        "align": "center"
                                    }
                                ]
                            },
                            {
                                "type": "Container",
                                "direction": "row",
                                "grow": 0,
                                "items": [
                                    {
                                        "type": "Text",
                                        "text": "${payload.musicManTemplateData.properties.PhotoAttribution}",
                                        "style": "textStyleVerySmall",
                                        "height": "100vw",
                                        "width": "100vw",
                                        "textAlign": "right",
                                        "paddingRight": 30
                                    }
                                ]
                            }
                        ]
                    },
                    {
                        "when": "${@viewportProfile == @hubLandscapeMedium}",
                        "type": "Container",
                        "width": "100vw",
                        "height": "100vh",
                        "items": [
                            {
                                "type": "Image",
                                "source": "${payload.musicManTemplateData.properties.BackgroundImageUrl}",
                                "scale": "best-fill",
                                "width": "100vw",
                                "height": "100vh",
                                "position": "absolute"
                            },
                            {
                                "type": "AlexaHeader",
                                "headerTitle": "${payload.musicManTemplateData.properties.Title}",
                                "headerAttributionImage": "${payload.musicManTemplateData.properties.LogoUrl}"
                            },
                            {
                                "type": "Container",
                                "direction": "row",
                                "paddingLeft": 40,
                                "paddingRight": 72,
                                "grow": 1,
                                "items": [
                                    {
                                        "type": "Container",
                                        "items": [
                                            {
                                                "when": "${payload.musicManTemplateData.properties.EventImageUrl != 'NA'}",
                                                "type": "Image",
                                                "source": "${payload.musicManTemplateData.properties.EventImageUrl}",
                                                "width": 340,
                                                "height": 360,
                                                "scale": "best-fit",
                                                "align": "top"
                                            },
                                            {
                                                "when": "${payload.musicManTemplateData.properties.EventImageUrl == 'NA'}",
                                                "type": "Image",
                                                "source": "${payload.musicManTemplateData.properties.GeneralSquareImageUrl}",
                                                "width": 340,
                                                "height": 360,
                                                "scale": "best-fit",
                                                "align": "top"
                                            }
                                        ]
                                    },
                                    {
                                        "type": "Container",
                                        "direction": "column",
                                        "paddingLeft": 15,
                                        "width": "63vw",
                                        "items": [
                                            {
                                                "type": "Text",
                                                "text": "<b>${payload.musicManTemplateData.properties.HeadingText}</b>",
                                                "style": "textStylePrimary2"
                                            },
                                            {
                                                "type": "Text",
                                                "text": "${payload.musicManTemplateData.properties.EventText[0]}",
                                                "paddingTop": 20,
                                                "style": "textStylePrimarySmall"
                                            },
                                            {
                                                "type": "Text",
                                                "text": "${payload.musicManTemplateData.properties.EventText[1]}",
                                                "paddingTop": 20,
                                                "style": "textStylePrimarySmall"
                                            },
                                            {
                                                "type": "Text",
                                                "text": "${payload.musicManTemplateData.properties.EventText[2]}",
                                                "paddingTop": 20,
                                                "style": "textStylePrimarySmall"
                                            }
                                        ]
                                    }
                                ]
                            },
                            {
                                "type": "Container",
                                "direction": "row",
                                "paddingRight": 150,
                                "paddingTop": 10,
                                "grow": 1,
                                "items": [
                                    {
                                        "type": "AlexaFooter",
                                        "footerHint": "${payload.musicManTemplateData.properties.HintString}",
                                        "height": 100
                                    },
                                    {
                                        "type": "Image",
                                        "source": "${payload.musicManTemplateData.properties.SongkickLogoUrl}",
                                        "width": 120,
                                        "height": 90,
                                        "scale": "best-fit",
                                        "align": "center"
                                    }
                                ]
                            },
                            {
                                "type": "Container",
                                "direction": "row",
                                "grow": 0,
                                "items": [
                                    {
                                        "type": "Text",
                                        "text": "${payload.musicManTemplateData.properties.PhotoAttribution}",
                                        "style": "textStyleVerySmall",
                                        "height": "100vw",
                                        "width": "100vw",
                                        "textAlign": "right",
                                        "paddingRight": 30
                                    }
                                ]
                            }
                        ]
                    },
                    {
                        "when": "${@viewportProfile == @hubLandscapeLarge}",
                        "type": "Container",
                        "width": "100vw",
                        "height": "100vh",
                        "items": [
                            {
                                "type": "Image",
                                "source": "${payload.musicManTemplateData.properties.BackgroundImageUrl}",
                                "scale": "best-fill",
                                "width": "100vw",
                                "height": "100vh",
                                "position": "absolute"
                            },
                            {
                                "type": "AlexaHeader",
                                "headerTitle": "${payload.musicManTemplateData.properties.Title}",
                                "headerAttributionImage": "${payload.musicManTemplateData.properties.LogoUrl}"
                            },
                            {
                                "type": "Container",
                                "direction": "row",
                                "paddingLeft": 40,
                                "paddingRight": 72,
                                "grow": 1,
                                "items": [
                                    {
                                        "type": "Container",
                                        "items": [
                                            {
                                                "when": "${payload.musicManTemplateData.properties.EventImageUrl != 'NA'}",
                                                "type": "Image",
                                                "source": "${payload.musicManTemplateData.properties.EventImageUrl}",
                                                "width": 300,
                                                "height": 300,
                                                "scale": "best-fit",
                                                "align": "top"
                                            },
                                            {
                                                "when": "${payload.musicManTemplateData.properties.EventImageUrl == 'NA'}",
                                                "type": "Image",
                                                "source": "${payload.musicManTemplateData.properties.GeneralSquareImageUrl}",
                                                "width": 300,
                                                "height": 300,
                                                "scale": "best-fit",
                                                "align": "top"
                                            }
                                        ]
                                    },
                                    {
                                        "type": "Container",
                                        "direction": "column",
                                        "paddingLeft": 15,
                                        "width": "63vw",
                                        "items": [
                                            {
                                                "type": "Text",
                                                "text": "<b>${payload.musicManTemplateData.properties.HeadingText}</b>",
                                                "style": "textStyleBody"
                                            },
                                            {
                                                "type": "Text",
                                                "style": "textStylePrimarySmall",
                                                "paddingTop": 20,
                                                "text": "${payload.musicManTemplateData.properties.EventText[0]}"
                                            },
                                            {
                                                "type": "Text",
                                                "style": "textStylePrimarySmall",
                                                "paddingTop": 20,
                                                "text": "${payload.musicManTemplateData.properties.EventText[1]}"
                                            },
                                            {
                                                "type": "Text",
                                                "style": "textStylePrimarySmall",
                                                "paddingTop": 20,
                                                "text": "${payload.musicManTemplateData.properties.EventText[2]}"
                                            }
                                        ]
                                    }
                                ]
                            },
                            {
                                "type": "Container",
                                "direction": "row",
                                "paddingRight": 150,
                                "paddingTop": 120,
                                "grow": 1,
                                "items": [
                                    {
                                        "type": "AlexaFooter",
                                        "footerHint": "${payload.musicManTemplateData.properties.HintString}",
                                        "height": 50
                                    },
                                    {
                                        "type": "Image",
                                        "source": "${payload.musicManTemplateData.properties.SongkickLogoUrl}",
                                        "width": 120,
                                        "height": 100,
                                        "scale": "best-fit",
                                        "align": "center"
                                    }
                                ]
                            },
                            {
                                "type": "Container",
                                "direction": "row",
                                "grow": 0,
                                "items": [
                                    {
                                        "type": "Text",
                                        "text": "${payload.musicManTemplateData.properties.PhotoAttribution}",
                                        "style": "textStyleVerySmall",
                                        "height": "100vw",
                                        "width": "100vw",
                                        "textAlign": "right",
                                        "paddingRight": 30
                                    }
                                ]
                            }
                        ]
                    },
                    {
                        "when": "${@viewportProfile == @tvLandscapeXLarge}",
                        "type": "Container",
                        "width": "100vw",
                        "height": "100vh",
                        "items": [
                            {
                                "type": "Image",
                                "source": "${payload.musicManTemplateData.properties.BackgroundImageUrl}",
                                "scale": "best-fill",
                                "width": "100vw",
                                "height": "100vh",
                                "position": "absolute"
                            },
                            {
                                "type": "AlexaHeader",
                                "headerTitle": "${payload.musicManTemplateData.properties.Title}",
                                "headerAttributionImage": "${payload.musicManTemplateData.properties.LogoUrl}"
                            },
                            {
                                "type": "Container",
                                "direction": "row",
                                "paddingLeft": 40,
                                "paddingRight": 72,
                                "grow": 1,
                                "items": [
                                    {
                                        "type": "Container",
                                        "items": [
                                            {
                                                "when": "${payload.musicManTemplateData.properties.EventImageUrl != 'NA'}",
                                                "type": "Image",
                                                "source": "${payload.musicManTemplateData.properties.EventImageUrl}",
                                                "width": 300,
                                                "height": 300,
                                                "scale": "best-fit",
                                                "align": "top"
                                            },
                                            {
                                                "when": "${payload.musicManTemplateData.properties.EventImageUrl == 'NA'}",
                                                "type": "Image",
                                                "source": "${payload.musicManTemplateData.properties.GeneralSquareImageUrl}",
                                                "width": 300,
                                                "height": 300,
                                                "scale": "best-fit",
                                                "align": "top"
                                            }
                                        ]
                                    },
                                    {
                                        "type": "Container",
                                        "direction": "column",
                                        "paddingLeft": 15,
                                        "width": "55vw",
                                        "items": [
                                            {
                                                "type": "Text",
                                                "text": "<b>${payload.musicManTemplateData.properties.HeadingText}</b>",
                                                "style": "textStylePrimary2"
                                            },
                                            {
                                                "type": "Text",
                                                "style": "textStylePrimarySmall",
                                                "paddingTop": 15,
                                                "text": "${payload.musicManTemplateData.properties.EventText[0]}"
                                            },
                                            {
                                                "type": "Text",
                                                "style": "textStylePrimarySmall",
                                                "paddingTop": 15,
                                                "text": "${payload.musicManTemplateData.properties.EventText[1]}"
                                            },
                                            {
                                                "type": "Text",
                                                "style": "textStylePrimarySmall",
                                                "paddingTop": 15,
                                                "text": "${payload.musicManTemplateData.properties.EventText[2]}"
                                            }
                                        ]
                                    }
                                ]
                            },
                            {
                                "type": "Container",
                                "direction": "row",
                                "paddingRight": 150,
                                "grow": 1,
                                "items": [
                                    {
                                        "type": "AlexaFooter",
                                        "footerHint": "${payload.musicManTemplateData.properties.HintString}",
                                        "height": 50
                                    },
                                    {
                                        "type": "Image",
                                        "source": "${payload.musicManTemplateData.properties.SongkickLogoUrl}",
                                        "width": 120,
                                        "height": 50,
                                        "scale": "best-fit",
                                        "align": "center"
                                    }
                                ]
                            },
                            {
                                "type": "Container",
                                "direction": "row",
                                "grow": 0,
                                "items": [
                                    {
                                        "type": "Text",
                                        "text": "${payload.musicManTemplateData.properties.PhotoAttribution}",
                                        "style": "textStyleVerySmall",
                                        "height": "100vw",
                                        "width": "100vw",
                                        "textAlign": "right",
                                        "paddingRight": 30
                                    }
                                ]
                            }
                        ]
                    }
                ]
            }
        },
        "mainTemplate": {
            "parameters": [
                "payload"
            ],
            "items": [
                {
                    "when": "${payload.musicManTemplateData.properties.LayoutToUse == 'Home'}",
                    "type": "Home"
                },
                {
                    "when": "${payload.musicManTemplateData.properties.LayoutToUse == 'Main'}",
                    "type": "Main"
                }
            ]
        }
    },
    "datasources": {
        "musicManTemplateData": {
            "type": "object",
            "objectId": "MusicManSample",
            "properties": {
                "Title": "The Music Man",
                "LayoutToUse": "Home",
                "HeadingText": "Here is where Iron Maiden is playing in July",
                "EventImageUrl": "NA",
                "HintString": "Where is Iron Maiden playing in July",
                "BackgroundImageUrl": "",
                "LogoUrl": "https://d3d9reei5h7cvh.cloudfront.net/MusicMan/MusicManIcon.png",
                "GeneralSquareImageUrl": "https://d3d9reei5h7cvh.cloudfront.net/MusicMan/Songkick340.png",
                "SongkickLogoUrl": "https://d3d9reei5h7cvh.cloudfront.net/MusicMan/SongkickConcerts.png",
                "EventText": [
                    "test1",
                    "test2",
                    "test3"
                ],
                "PhotoAttribution": "Background photo: ",
                "BackgroundImages": [
                    "https://d3d9reei5h7cvh.cloudfront.net/MusicMan/ArtemBryzgalov-1588884248337.jpg|Artem Bryzgalov",
                    "https://d3d9reei5h7cvh.cloudfront.net/MusicMan/FrankieCordoba-1508252498500.jpg|Frankie Cordoba",
                    "https://d3d9reei5h7cvh.cloudfront.net/MusicMan/JacquesGollnick-1519736927049.jpg|Jacques Gollnick",
                    "https://d3d9reei5h7cvh.cloudfront.net/MusicMan/KeaganHenman-1559656443.jpg|Keagan Henman",
                    "https://d3d9reei5h7cvh.cloudfront.net/MusicMan/MarkdeJong-1563628555540.jpg|Mark de Jong",
                    "https://d3d9reei5h7cvh.cloudfront.net/MusicMan/ParkerCoffman-1581742009630.jpg|Parker Coffman",
                    "https://d3d9reei5h7cvh.cloudfront.net/MusicMan/VishnuNair-1524368535928.jpg|Vishnu Nair",
                    "https://d3d9reei5h7cvh.cloudfront.net/MusicMan/WesleyTingey-1553819282.jpg|Wesley Tingey",
                    "https://d3d9reei5h7cvh.cloudfront.net/MusicMan/YvettedeWit-1470229538611.jpg|Yvette de Wit",
                    "https://d3d9reei5h7cvh.cloudfront.net/MusicMan/YvettedeWit-1470229722913.jpg|Yvette de Wit"
                ]
            },
            "transformers": [
                {
                    "inputPath": "HintString",
                    "transformer": "textToHint"
                }
            ]
        }
    },
    "sources": {}
}